qbusyindicator/__init__.py
qbusyindicator/busyindicator.py
qbusyindicator/examples/__init__.py
qbusyindicator/examples/demo.py
qbusyindicator/examples/loading.gif
pyside6_overlay_busy_indicator-1.6.dist-info/LICENSE.txt
pyside6_overlay_busy_indicator-1.6.dist-info/METADATA
pyside6_overlay_busy_indicator-1.6.dist-info/WHEEL
pyside6_overlay_busy_indicator-1.6.dist-info/top_level.txt
pyside6_overlay_busy_indicator-1.6.dist-info/RECORD
