Metadata-Version: 2.1
Name: pyside6-overlay-busy-indicator
Version: 1.6
Summary: A customizable overlay busy indicator with a smooth fade animation for PySide6
Home-page: https://github.com/pohemati/pyside6-overlay-busy-indicator
Download-URL: https://github.com/pohemati/pyside6-overlay-busy-indicator/archive/refs/tags/v1.6.tar.gz
Author: Poria Hemati
Author-email: poria.hemati@gmail.com
License: MIT
Keywords: pyside6,overlay,busy,indicator,progressbar,loading
Classifier: Operating System :: OS Independent
Classifier: License :: OSI Approved :: MIT License
Classifier: Programming Language :: Python :: 3
License-File: LICENSE.txt
Requires-Dist: PySide6
